NPC/__init__.py
NPC-1.351.dist-info/License.txt
NPC-1.351.dist-info/METADATA
NPC-1.351.dist-info/WHEEL
NPC-1.351.dist-info/top_level.txt
NPC-1.351.dist-info/RECORD
