Metadata-Version: 1.0
Name: NPC
Version: 1.351
Summary: Parallel Processing in Network Devices
Home-page: https://ntp.perity.site
Author: Dipnarayan Das
Author-email: dipnarayan.das35@gmail.com
License: License.txt
Platform: UNKNOWN
